{
  "model_info": {
    "model_type": "lstm",
    "crypto_symbol": "BTC",
    "model_version": "20250728_121434",
    "created_at": "2025-07-28T12:14:34.121371",
    "framework": "tensorflow"
  },
  "training_metrics": {
    "training_duration_seconds": 3.86121,
    "final_loss": 17.73499870300293,
    "final_val_loss": 16.58701515197754,
    "final_mae": 0.9614406824111938,
    "final_val_mae": 0.37979668378829956,
    "epochs_trained": 1,
    "best_epoch": "1",
    "training_completed_at": "2025-07-28T12:14:33.600541",
    "mse": 30573366.757028386,
    "mae": 5167.089739583334,
    "rmse": 5529.318833005417,
    "r2_score": -6.904529480616411,
    "mape": 10.23257302530039
  },
  "features": {
    "feature_names": [
      "price_features",
      "price_features"
    ],
    "feature_count": 2,
    "feature_engineering": {}
  },
  "training_config": {
    "epochs": 1,
    "batch_size": 32,
    "sequence_length": 10
  },
  "data_info": {
    "features_count": 2,
    "data_points": 249
  },
  "model_status": "trained",
  "last_updated": "2025-07-28T12:14:34.121371"
}